{
	"type": "Styles",
	"styles": [
		{
			"type": "Style",
			"name": "Building",
			"description": "No pop-ups for buildings",
			"onTags": [ { "building": "*" } ],
			"style": { "popup": "no" }
		},
		{
			"type": "Style",
			"name": "Building",
			"description": "Buildings",
			"onTags": [ { "building": "*" }, { "building:part": "*" } ],
			"style": { "color": "#ADA5A5", "opacity": 1, "weight": 1, "fillColor": "#D4CACA", "fillOpacity": 1, "layer": -2 }
		},
		{
			"type": "Style",
			"name": "Room",
			"description": "Indoor rooms",
			"onTags": [ { "indoor": "room" }, { "room": "*" }, { "buildingpart": "room" } ],
			"style": { "color": "#AAAAAA", "opacity": 1, "weight": 0.8, "fillColor": "#E0E0E0", "fillOpacity": 1, "layer": -1, "popup": "yes" }
		},
		{
			"type": "Style",
			"name": "Wall",
			"description": "Indoor rooms",
			"onTags": [ { "indoor": "wall" }, { "buildingpart": "wall" }, { "barrier": "wall" } ],
			"style": { "color": "#999999", "opacity": 1, "weight": 2, "fillColor": "red", "fillOpacity": 1, "popup": "yes" }
		},
		{
			"type": "Style",
			"name": "Path",
			"description": "Highways (default)",
			"onTags": [ { "highway": "*" } ],
			"style": { "color": "#F98072", "opacity": 0.2 }
		},
		{
			"type": "Style",
			"name": "Oneway path",
			"description": "Oneway path",
			"onTags": [ { "oneway": "yes" }, { "conveying": "forward" } ],
			"style": { "icon": "img/arrow1_up.svg", "rotateIcon": true }
		},
		{
			"type": "Style",
			"name": "Oneway path",
			"description": "Oneway path",
			"onTags": [ { "oneway": "-1" }, { "conveying": "backward" } ],
			"style": { "icon": "img/arrow1_down.svg", "rotateIcon": true }
		},
		{
			"type": "Style",
			"name": "Area",
			"description": "Indoor areas ('OR' example for values)",
			"onTags": [ { "indoor": "area|corridor" }, { "highway": "pedestrian|footway", "area": "yes" }, { "buildingpart": "corridor|hall" }, { "room": "corridor|entrance|hall|entry|gallery" } ],
			"style": { "color": "#AAAAAA", "opacity": 1, "weight": 0.8, "fillColor": "#EEEEEE", "fillOpacity": 1, "layer": -1 }
		},
		{
			"type": "Style",
			"name": "Room",
			"description": "Room icons",
			"onTags": [ { "room": "*" } ],
			"style": { "icon": "img/room_${room}.svg", "showMissingIcon": false }
		},
		{
			"type": "Style",
			"name": "Computer lab",
			"description": "Computer laboratory icon",
			"onTags": [ { "room": "laboratory", "laboratory": "computer" } ],
			"style": { "icon": "img/room_computer.svg" }
		},
		{
			"type": "Style",
			"name": "Biology laboratory",
			"description": "Biology laboratory",
			"onTags": [ { "room": "laboratory", "laboratory": "biology|biological" } ],
			"style": { "icon": "img/Biohazard_symbol.svg" }
		},
		{
			"type": "Style",
			"name": "Physics laboratory",
			"description": "Physics laboratory",
			"onTags": [ { "room": "laboratory", "laboratory": "physical" } ],
			"style": { "icon": "img/physics.svg" }
		},
		{
			"type": "Style",
			"name": "Electronics laboratory",
			"description": "Electronics laboratory",
			"onTags": [ { "room": "laboratory", "laboratory": "electronics|electronic" } ],
			"style": { "icon": "img/Octicons-circuit-board.svg" }
		},
		{
			"type": "Style",
			"name": "Amphitheatre",
			"description": "Amphitheatre",
			"onTags": [ { "room": "amphitheatre" } ],
			"style": { "icon": "img/room_auditorium.svg" }
		},
		{
			"type": "Style",
			"name": "Reception",
			"description": "Reception",
			"onTags": [ { "room": "reception" } ],
			"style": { "icon": "img/room_administration.svg" }
		},
		{
			"type": "Style",
			"name": "Refectory",
			"description": "Refectory",
			"onTags": [ { "room": "refectory" } ],
			"style": { "icon": "img/room_restaurant.svg" }
		},
		{
			"type": "Style",
			"name": "Grass",
			"description": "Grass landuse",
			"onTags": [ { "landuse": "grass" } ],
			"style": { "opacity": 0, "weight": 0, "fillColor": "#CFECA8", "fillOpacity": 1, "layer": -1 }
		},
		{
			"type": "Style",
			"name": "Historic",
			"description": "Historic element",
			"onTags": [ { "historic": "yes" } ],
			"style": { "color": "#C0B0A2", "opacity": 0.5, "weight": 0.5, "fillColor": "#C0B0A2", "fillOpacity": 0.5, "layer": -1 }
		},
		{
			"type": "Style",
			"name": "Platform",
			"description": "Railway platform",
			"onTags": [ { "railway": "platform" }, { "public_transport": "platform" } ],
			"style": { "color": "#B4ADB3", "opacity": 1, "weight": 1, "fillColor": "#BABABA", "fillOpacity": 1, "icon": "img/Bahn_aus_Zusatzzeichen_1024-15_A.png", "layer": -1 }
		},
		{
			"type": "Style",
			"name": "Door",
			"description": "Door nodes ('OR' example for tags)",
			"onTags": [ { "door": "*" }, { "entrance": "*" }, { "buildingpart": "door" } ],
			"style": { "icon": "img/door.svg" }
		},
		{
			"type": "Style",
			"name": "Passage",
			"description": "Door=no nodes",
			"onTags": [ { "door": "no" } ],
			"style": { "icon": "img/door_no.svg" }
		},
		{
			"type": "Style",
			"name": "Subway entrance",
			"description": "Subway entrance",
			"onTags": [ { "railway": "subway_entrance" } ],
			"style": { "icon": "img/subway.svg" }
		},
		{
			"type": "Style",
			"name": "Sliding door",
			"description": "Door=sliding nodes",
			"onTags": [ { "door": "sliding" } ],
			"style": { "icon": "img/door_sliding.svg" }
		},
		{
			"type": "Style",
			"name": "Emergency exit",
			"description": "Emergency exit",
			"onTags": [ { "entrance": "emergency" } ],
			"style": { "icon": "img/emergency_door.svg" }
		},
		{
			"type": "Style",
			"name": "Amenity",
			"description": "Amenities, shops (default)",
			"onTags": [ { "amenity": "*" }, { "shop": "*" } ],
			"style": { "color": "red", "fillColor": "orange" }
		},
		{
			"type": "Style",
			"name": "Amenity",
			"description": "Amenities icons",
			"onTags": [ { "amenity": "*" } ],
			"style": { "icon": "img/amenity_${amenity}.png" }
		},
		{
			"type": "Style",
			"name": "Shop",
			"description": "Shopping icons",
			"onTags": [ { "shop": "*" } ],
			"style": { "icon": "img/shopping_${shop}.png" }
		},
		{
			"type": "Style",
			"name": "Barrier",
			"description": "Barrier icons",
			"onTags": [ { "barrier": "*" } ],
			"style": { "icon": "img/barrier_${barrier}.png", "showMissingIcon": false }
		},
		{
			"type": "Style",
			"name": "Tourism",
			"description": "Tourism icons",
			"onTags": [ { "tourism": "*" } ],
			"style": { "icon": "img/tourism_${tourism}.png" }
		},
		{
			"type": "Style",
			"name": "Information",
			"description": "Information icons",
			"onTags": [ { "information": "*" } ],
			"style": { "icon": "img/information_${information}.png" }
		},
		{
			"type": "Style",
			"name": "Airport",
			"description": "Aeroway icons",
			"onTags": [ { "aeroway": "*" } ],
			"style": { "icon": "img/aeroway_${aeroway}.png" }
		},
		{
			"type": "Style",
			"name": "Ticket validator",
			"description": "Ticket validator",
			"onTags": [ { "amenity": "ticket_validator" } ],
			"style": { "icon": "img/tickets_valid.svg" }
		},
		{
			"type": "Style",
			"name": "Ticket vending",
			"description": "Ticket vending machine ('AND' example for tags)",
			"onTags": [ { "amenity": "vending_machine", "vending": "public_transport_tickets" } ],
			"style": { "icon": "img/tickets_vending.svg" }
		},
		{
			"type": "Style",
			"name": "Newspapers vending",
			"description": "Newspapers vending machine",
			"onTags": [ { "amenity": "vending_machine", "vending": "newspapers" },  { "amenity": "vending_machine", "vending": "news_papers" }, { "shop": "newsagent" } ],
			"style": { "icon": "img/Farm-Fresh_newspaper.png" }
		},
		{
			"type": "Style",
			"name": "Bus stop",
			"description": "Bus stop",
			"onTags": [ { "highway": "bus_stop" } ],
			"style": { "icon": "img/highway_bus_stop.png" }
		},
		{
			"type": "Style",
			"name": "Stairs",
			"description": "Stairs",
			"onTags": [ { "highway": "steps" } ],
			"style": { "color": "#F98072", "opacity": 1, "weight": 10, "lineCap": "butt", "dashArray": "2,1", "levelup": true }
		},
		{
			"type": "Style",
			"name": "Conveying stairs",
			"description": "Conveying stairs",
			"onTags": [ { "highway": "steps", "conveying": "yes|forward|backward" } ],
			"style": { "color": "#848484", "opacity": 1, "weight": 10, "lineCap": "butt", "dashArray": "3,1" }
		},
		{
			"type": "Style",
			"name": "Vertical passage",
			"description": "Elevetor, stairs (as polygons)",
			"onTags": [ { "highway": "elevator|lift" }, { "buildingpart": "verticalpassage" }, { "room": "stairs" } ],
			"style": { "color": "#B3986C", "fillColor": "#EFCB90", "opacity": 1, "fillOpacity": 1, "weight": 1, "levelup": true }
		},
		{
			"type": "Style",
			"name": "Elevator",
			"description": "Elevator",
			"onTags": [ { "highway": "elevator|lift" }, { "buildingpart:verticalpassage": "elevator" } ],
			"style": { "icon": "img/Elevator_icon.png" }
		},
		{
			"type": "Style",
			"name": "Stairs",
			"description": "Stairs (verticalpassage)",
			"onTags": [ { "buildingpart:verticalpassage": "stairway" }, { "room": "stairs" } ],
			"style": { "icon": "img/NingboRT_Stairs_Logo.svg" }
		},
		{
			"type": "Style",
			"name": "Emergency stairs",
			"description": "Stairs for emergency only (as polygons)",
			"onTags": [ { "buildingpart": "verticalpassage", "access": "emergency" } ],
			"style": { "color": "#009262", "fillColor": "#C0FFCB", "icon": "img/Emergency_stairs.svg" }
		},
		{
			"type": "Style",
			"name": "Escalator",
			"description": "Escalator (verticalpassage)",
			"onTags": [ { "buildingpart:verticalpassage": "escalator" }, { "room": "escalator" } ],
			"style": { "icon": "img/Aiga_escalator_mirror.svg" }
		},
		{
			"type": "Style",
			"name": "Subway",
			"description": "Subway rails",
			"onTags": [ { "railway": "subway" } ],
			"style": { "color": "#888888", "opacity": 1, "weight": 10, "lineCap": "butt", "dashArray": "5,5" }
		},
		{
			"type": "Style",
			"name": "Fence",
			"description": "Fence",
			"onTags": [ { "barrier": "fence" } ],
			"style": { "color": "#5B5B5B", "opacity": 1, "weight": 5, "lineCap": "butt", "icon": "no" }
		},
		{
			"type": "Style",
			"name": "Hedge",
			"description": "Hedge",
			"onTags": [ { "barrier": "hedge" } ],
			"style": { "color": "#8CD16E", "opacity": 1, "weight": 5, "lineCap": "butt", "icon": "no" }
		},
		{
			"type": "Style",
			"name": "Turnstile",
			"description": "Turnstile",
			"onTags": [ { "barrier": "turnstile" } ],
			"style": { "icon": "img/barrier_turnstile.svg" }
		},
		{
			"type": "Style",
			"name": "Pillar",
			"description": "Pillar",
			"onTags": [ { "man_made": "pillar" }, { "buildingpart": "pillar" }, { "building:part": "column" }, { "indoor": "column" } ],
			"style": { "color": "#A8A8A8", "opacity": 1, "weight": 5, "lineCap": "butt", "fillColor": "#A8A8A8", "fillOpacity": 1, "radius": 4, "layer": 0 }
		},
		{
			"type": "Style",
			"name": "Statue",
			"description": "Statue icons",
			"onTags": [ { "artwork_type": "statue|sculpture|stone|bust" } ],
			"style": { "icon": "img/statue.svg" }
		},
		{
			"type": "Style",
			"name": "Information",
			"description": "Information for travelers",
			"onTags": [ { "tourism": "information" } ],
			"style": { "icon": "img/Infobox_info_icon.svg" }
		},
		{
			"type": "Style",
			"name": "Map",
			"description": "Map",
			"onTags": [ { "information": "map" } ],
			"style": { "icon": "img/map_default.svg" }
		},
		{
			"type": "Style",
			"name": "Street map",
			"description": "Map",
			"onTags": [ { "information": "map", "map_type": "street" } ],
			"style": { "icon": "img/map_street.svg" }
		},
		{
			"type": "Style",
			"name": "Scheme map",
			"description": "Map",
			"onTags": [ { "information": "map", "map_type": "scheme" } ],
			"style": { "icon": "img/map_scheme.svg" }
		},
		{
			"type": "Style",
			"name": "Advert",
			"description": "Advertising",
			"onTags": [ { "advertising": "*" } ],
			"style": { "icon": "img/advertising.svg" }
		},
		{
			"type": "Style",
			"name": "Emergency phone",
			"description": "Emergency phone",
			"onTags": [ { "emergency": "phone" } ],
			"style": { "icon": "img/PublicInformationSymbol_EmergencyTelephone.svg" }
		},
		{
			"type": "Style",
			"name": "CCTV",
			"description": "Surveillance",
			"onTags": [ { "man_made": "surveillance" } ],
			"style": { "icon": "img/Video_surveillance_logo.svg" }
		},
		{
			"type": "Style",
			"name": "Tomb",
			"description": "Tomb",
			"onTags": [ { "historic": "tomb" } ],
			"style": { "icon": "img/historic_tomb.png" }
		}
	]
}